{
    "cookies": [
        {
            "name": "locale",
            "value": "vi_VN",
            "domain": ".facebook.com",
            "path": "/",
            "expires": 1772592686.075661,
            "httpOnly": false,
            "secure": true,
            "sameSite": "None"
        },
        {
            "name": "sb",
            "value": "p2OeaRe6tRBhTeOzrr9-vMEC",
            "domain": ".facebook.com",
            "path": "/",
            "expires": 1806896421.615576,
            "httpOnly": true,
            "secure": true,
            "sameSite": "None"
        },
        {
            "name": "ps_l",
            "value": "1",
            "domain": ".facebook.com",
            "path": "/",
            "expires": 1806575149.253061,
            "httpOnly": true,
            "secure": true,
            "sameSite": "Lax"
        },
        {
            "name": "ps_n",
            "value": "1",
            "domain": ".facebook.com",
            "path": "/",
            "expires": 1806575149.253155,
            "httpOnly": true,
            "secure": true,
            "sameSite": "None"
        },
        {
            "name": "datr",
            "value": "yu6fafmjxt2zFnvJ2rjSXhXW",
            "domain": ".facebook.com",
            "path": "/",
            "expires": 1806649033.708265,
            "httpOnly": true,
            "secure": true,
            "sameSite": "None"
        },
        {
            "name": "c_user",
            "value": "61578773456852",
            "domain": ".facebook.com",
            "path": "/",
            "expires": 1803954524.089252,
            "httpOnly": false,
            "secure": true,
            "sameSite": "None"
        },
        {
            "name": "wd",
            "value": "1920x1080",
            "domain": ".facebook.com",
            "path": "/",
            "expires": 1773023335,
            "httpOnly": false,
            "secure": true,
            "sameSite": "Lax"
        },
        {
            "name": "fr",
            "value": "1wVrAztKgCVysrXlm.AWe1aT2rW76CGKZw2BFdppm_cQzFqfsbAJJmHmsUWqvJ5K6KSRE.BppPXb..AAA.0.0.BppPXb.AWel__QMLPmML5tbhyFLYWBvvbc",
            "domain": ".facebook.com",
            "path": "/",
            "expires": 1780194524.089525,
            "httpOnly": true,
            "secure": true,
            "sameSite": "None"
        },
        {
            "name": "xs",
            "value": "19%3AHHEBJZQLqUVBsg%3A2%3A1772336424%3A-1%3A-1%3A%3AAcx9e1pzZp8umXvDQjXrcFMiSrfTWjJokWPcJ5c9k3k",
            "domain": ".facebook.com",
            "path": "/",
            "expires": 1803954524.089731,
            "httpOnly": true,
            "secure": true,
            "sameSite": "None"
        },
        {
            "name": "presence",
            "value": "C%7B%22t3%22%3A%5B%5D%2C%22utc3%22%3A1772418527058%2C%22v%22%3A1%7D",
            "domain": ".facebook.com",
            "path": "/",
            "expires": -1,
            "httpOnly": false,
            "secure": true,
            "sameSite": "Lax"
        },
        {
            "name": "alsfid",
            "value": "{\"id\":\"f8ca240fc\",\"timestamp\":1772418535799.5999}",
            "domain": ".facebook.com",
            "path": "/",
            "expires": 1772418595.79999,
            "httpOnly": false,
            "secure": false,
            "sameSite": "Lax"
        }
    ]
}