{
    "cookies": [
        {
            "name": "locale",
            "value": "vi_VN",
            "domain": ".facebook.com",
            "path": "/",
            "expires": 1772605322.29672,
            "httpOnly": false,
            "secure": true,
            "sameSite": "None"
        },
        {
            "name": "sb",
            "value": "A5WeabNUien_-Qfi5jUwidt0",
            "domain": ".facebook.com",
            "path": "/",
            "expires": 1806649189.778005,
            "httpOnly": true,
            "secure": true,
            "sameSite": "None"
        },
        {
            "name": "ps_l",
            "value": "1",
            "domain": ".facebook.com",
            "path": "/",
            "expires": 1806560522.700927,
            "httpOnly": true,
            "secure": true,
            "sameSite": "Lax"
        },
        {
            "name": "ps_n",
            "value": "1",
            "domain": ".facebook.com",
            "path": "/",
            "expires": 1806560522.701046,
            "httpOnly": true,
            "secure": true,
            "sameSite": "None"
        },
        {
            "name": "datr",
            "value": "Fu-fadSOkMGaQOLEVP_uMHHp",
            "domain": ".facebook.com",
            "path": "/",
            "expires": 1806649110.845865,
            "httpOnly": true,
            "secure": true,
            "sameSite": "None"
        },
        {
            "name": "c_user",
            "value": "61578889611234",
            "domain": ".facebook.com",
            "path": "/",
            "expires": 1803651086.984243,
            "httpOnly": false,
            "secure": true,
            "sameSite": "None"
        },
        {
            "name": "wd",
            "value": "1536x864",
            "domain": ".facebook.com",
            "path": "/",
            "expires": 1772719886,
            "httpOnly": false,
            "secure": true,
            "sameSite": "Lax"
        },
        {
            "name": "presence",
            "value": "C%7B%22t3%22%3A%5B%5D%2C%22utc3%22%3A1772115083703%2C%22v%22%3A1%7D",
            "domain": ".facebook.com",
            "path": "/",
            "expires": -1,
            "httpOnly": false,
            "secure": true,
            "sameSite": "Lax"
        },
        {
            "name": "fr",
            "value": "1RKtNsvqpqlP9vvJQ.AWeTh5W8_1LoiSEOyqqviSU5FMbKVGezexZpBWJVfMvxcLdPqrg.BpoFSP..AAA.0.0.BpoFSP.AWfocFNrCgpeO2mqkXinP8Z5W5o",
            "domain": ".facebook.com",
            "path": "/",
            "expires": 1779891086.984324,
            "httpOnly": true,
            "secure": true,
            "sameSite": "None"
        },
        {
            "name": "xs",
            "value": "12%3A6uym1Ix_Ld0eUA%3A2%3A1772089187%3A-1%3A-1%3A%3AAcy-g4b6lA5fgJ3E-YGuEsCXSZphu341IGkVxHR1YcA",
            "domain": ".facebook.com",
            "path": "/",
            "expires": 1803651086.984391,
            "httpOnly": true,
            "secure": true,
            "sameSite": "None"
        },
        {
            "name": "alsfid",
            "value": "{\"id\":\"fd78b4aa2\",\"timestamp\":1772115091131.2998}",
            "domain": ".facebook.com",
            "path": "/",
            "expires": 1772115151.131584,
            "httpOnly": false,
            "secure": false,
            "sameSite": "Lax"
        }
    ]
}